classdiff/config.py
classdiff/diff_range.py
classdiff/graphviz.py
classdiff/main.py
classdiff/tag_language.py
classdiff/tag_model.py
gitk_class_diagram-1.0.0.data/scripts/gitk-cl
gitk_class_diagram-1.0.0.dist-info/LICENSE
gitk_class_diagram-1.0.0.dist-info/METADATA
gitk_class_diagram-1.0.0.dist-info/WHEEL
gitk_class_diagram-1.0.0.dist-info/entry_points.txt
gitk_class_diagram-1.0.0.dist-info/top_level.txt
gitk_class_diagram-1.0.0.dist-info/RECORD
